cfa_distributions
