Metadata-Version: 1.0
Name: cfa-distributions
Version: 1.1
Summary: Gaussian and Binomial distributions
Home-page: UNKNOWN
Author: Deric Atienza
Author-email: dericatienza@live.com.ph
License: UNKNOWN
Platform: UNKNOWN
